setup.py
awslib/__init__.py
awslib/ec2.py
awslib/s3.py
awslib.egg-info/PKG-INFO
awslib.egg-info/SOURCES.txt
awslib.egg-info/dependency_links.txt
awslib.egg-info/requires.txt
awslib.egg-info/top_level.txt