Metadata-Version: 1.0
Name: awslib
Version: 0.2
Summary: Small library providing Amazon Web Services utility functions on top of boto
Home-page: UNKNOWN
Author: James Aylett
Author-email: james@tartarus.org
License: MIT
Platform: UNKNOWN
Classifier: Intended Audience :: Developers
Classifier: License :: OSI Approved :: MIT License
Classifier: Programming Language :: Python :: 2
